vital_sqi/__init__.py
vital_sqi/app/__init__.py
vital_sqi/app/app.py
vital_sqi/app/index.py
vital_sqi/app/views/__init__.py
vital_sqi/app/views/dashboard1.py
vital_sqi/app/views/dashboard2.py
vital_sqi/app/views/dashboard3.py
vital_sqi/common/__init__.py
vital_sqi/common/band_filter.py
vital_sqi/common/generate_template.py
vital_sqi/common/power_spectrum.py
vital_sqi/common/rpeak_detection.py
vital_sqi/common/utils.py
vital_sqi/data/__init__.py
vital_sqi/data/signal_io.py
vital_sqi/data/signal_sqi_class.py
vital_sqi/dataset/__init__.py
vital_sqi/dataset/example_data.py
vital_sqi/pipeline/__init__.py
vital_sqi/pipeline/pipeline_functions.py
vital_sqi/pipeline/pipeline_highlevel.py
vital_sqi/preprocess/__init__.py
vital_sqi/preprocess/preprocess_signal.py
vital_sqi/preprocess/removal_utilities.py
vital_sqi/preprocess/segment_split.py
vital_sqi/rule/__init__.py
vital_sqi/rule/rule_class.py
vital_sqi/rule/ruleset_class.py
vital_sqi/sqi/__init__.py
vital_sqi/sqi/dtw_sqi.py
vital_sqi/sqi/hrv_sqi.py
vital_sqi/sqi/rpeaks_sqi.py
vital_sqi/sqi/standard_sqi.py
vital_sqi/sqi/waveform_sqi.py
vital_sqi-0.1.0.dist-info/LICENSE
vital_sqi-0.1.0.dist-info/METADATA
vital_sqi-0.1.0.dist-info/WHEEL
vital_sqi-0.1.0.dist-info/top_level.txt
vital_sqi-0.1.0.dist-info/RECORD
