Metadata-Version: 2.1
Name: vital-sqi
Version: 0.1.0
Summary: Signal quality control pipeline for electrocardiogram and photoplethysmogram
Home-page: https://github.com/meta00/vital_sqi
Author: Khoa Le, Hai Ho, Stefan Karolcik, Heloise Greeff
Author-email: khoaldv@oucru.org, haihb@oucru.org, s.karolcik@imperial.ac.uk, heloise.greeff@eng.ox.ac.uk
Maintainer: Hai Ho, Khoa Le
Maintainer-email: haihb@oucru.org, khoaldv@oucru.org
License: MIT
Platform: UNKNOWN
Classifier: Intended Audience :: Developers
Classifier: Operating System :: OS Independent
Classifier: Programming Language :: Python :: 3
Classifier: Programming Language :: Python :: 3.7
Classifier: Programming Language :: Python :: 3.8
Requires-Python: >=3.7
Requires-Dist: librosa (>=0.9.2)
Requires-Dist: heartpy (>=1.2.6)
Requires-Dist: pmdarima (>=1.8.0)
Requires-Dist: hrv-analysis (>=1.0.3)
Requires-Dist: matplotlib (>=3.3.3)
Requires-Dist: numpy (>=1.20.2)
Requires-Dist: pandas (>=1.1.5)
Requires-Dist: plotly (>=4.14.3)
Requires-Dist: scikit-learn (>=0.24.1)
Requires-Dist: scipy (>=1.6.0)
Requires-Dist: statsmodels (>=0.12.1)
Requires-Dist: tqdm (>=4.56.0)
Requires-Dist: py-ecg-detectors (>=1.0.2)
Requires-Dist: pyEDFlib (>=0.1.20)
Requires-Dist: pycwt (>=0.3.0a22)
Requires-Dist: wfdb (>=3.3.0)
Requires-Dist: datetimerange (>=1.0.0)
Requires-Dist: dateparser (>=1.0.0)
Requires-Dist: openpyxl (>=3.0.7)
Requires-Dist: pyflowchart (>=0.1.3)
